[
  {
    "href": "http://www.carwale.com/mitsubishi-cars/pajerosport/",
    "name": "Mitsubishi Pajero Sport"
  },
  {
    "discontinued": true,
    "href": "http://www.carwale.com/mitsubishi-cars/cedia-2006-2009/",
    "name": "Mitsubishi Cedia [2006-2009]"
  },
  {
    "discontinued": true,
    "href": "http://www.carwale.com/mitsubishi-cars/challenger/",
    "name": "Mitsubishi Challenger"
  },
  {
    "discontinued": true,
    "href": "http://www.carwale.com/mitsubishi-cars/lancer-2004-2012/",
    "name": "Mitsubishi Lancer [2004-2012]"
  },
  {
    "discontinued": true,
    "href": "http://www.carwale.com/mitsubishi-cars/montero-2007-2012/",
    "name": "Mitsubishi Montero [2007-2012]"
  },
  {
    "discontinued": true,
    "href": "http://www.carwale.com/mitsubishi-cars/pajero/",
    "name": "Mitsubishi Pajero"
  },
  {
    "discontinued": true,
    "href": "http://www.carwale.com/mitsubishi-cars/cedia-2009-2013/",
    "name": "Mitsubishi Cedia [2009-2013]"
  },
  {
    "discontinued": true,
    "href": "http://www.carwale.com/mitsubishi-cars/outlander-2012-2013/",
    "name": "Mitsubishi Outlander [2012-2013]"
  },
  {
    "discontinued": true,
    "href": "http://www.carwale.com/mitsubishi-cars/montero-2009-2014/",
    "name": "Mitsubishi Montero [2009-2014]"
  },
  {
    "discontinued": true,
    "href": "http://www.carwale.com/mitsubishi-cars/lancerevolution20112013/",
    "name": "Mitsubishi Lancer Evolution [2011-2013]"
  }
]